xaal/__init__.py
xaal/yeelight/__init__.py
xaal/yeelight/__main__.py
xaal/yeelight/devices.py
xaal/yeelight/gw.py
xaal_yeelight-0.3.2.dist-info/METADATA
xaal_yeelight-0.3.2.dist-info/WHEEL
xaal_yeelight-0.3.2.dist-info/top_level.txt
xaal_yeelight-0.3.2.dist-info/RECORD
