Metadata-Version: 2.4
Name: xaal.yeelight
Version: 0.3.2
Summary: xAAL gateway for Yeelight devices
Author-email: Jerome Kerdreux <Jerome.Kerdreux@imt-atlantique.fr>
License-Expression: GPL-3.0-or-later
Project-URL: Homepage, https://recherche.imt-atlantique.fr/xaal/
Project-URL: Documentation, https://gitlab.imt-atlantique.fr/xaal/code/python/-/blob/main/devices/protocols/Yeelight/README.rst
Project-URL: Source, https://gitlab.imt-atlantique.fr/xaal/code/python/-/tree/main/devices/protocols/Yeelight
Keywords: xaal,yeelight
Classifier: Programming Language :: Python
Classifier: Topic :: Home Automation
Requires-Dist: xaal.lib
Requires-Dist: xaal.schemas
Requires-Dist: gevent
Requires-Dist: yeelight
Requires-Dist: decorator
